<?xml version='1.0' encoding='utf-8'?>
<!DOCTYPE hibernate-configuration
        PUBLIC "-//Hibernate/Hibernate Configuration DTD//EN"
        "http://www.hibernate.org/dtd/hibernate-configuration-3.0.dtd">

<hibernate-configuration>
    <session-factory>
        <property name="hibernate.dialect">org.hibernate.dialect.PostgresPlusDialect</property>

        <property name="connection.url">jdbc:postgresql://localhost:5432/example</property>
        <property name="connection.driver_class">org.postgresql.Driver</property>
        <property name="connection.username">postgres</property>
        <property name="connection.password">admin</property>

        <property name="hbm2ddl.auto">update</property>
        <property name="show_sql">true</property>
        <property name="format_sql">true</property>

        <mapping class="many.to.one.Person"/>
        <mapping class="many.to.one.Car"/>

        <mapping class="unidirectional.one.to.many.Customer"/>
        <mapping class="unidirectional.one.to.many.Order"/>

        <mapping class="bidirectional.many.to.many.Employee"/>
        <mapping class="bidirectional.many.to.many.Project"/>
    </session-factory>
</hibernate-configuration>